{
  "cate": "5",
  "date": "3æ29æ¥ 6æ41å",
  "datetime": "2018-03-29T06:41",
  "video": "",
  "duration": 0,
  "img": "html/20180329/K10011383361_1803290628_1803290640_01_02.jpg",
  "title": "パリの観光名所 ＶＲで空中散歩",
  "summary": "仮想の世界を現実のように体験できるＶＲ＝バーチャルリアリティーの技術を使い、エッフェル塔や凱旋門などパリの観光名所の空からの風景を楽しむことができる施設がパリにオープンすることになり、これまでとは少し違った観光が楽しめると話題を集めそうです。",
  "more": "",
  "body": [
    {
      "title": "",
      "img": "html/20180329/K10011383361_1803290628_1803290640_01_03.jpg",
      "align": "",
      "text": "今月末のオープンを前に報道関係者などに公開されたパリ市内の施設では、ＶＲ＝バーチャルリアリティーの技術を活用し、建物の中にいながらパリの観光名所の風景を楽しむことができます。<br /><br />利用客は映像が映し出される専用のゴーグル型の端末を身につけ、１３分間かけてエッフェル塔や凱旋門、それにノートルダム寺院など世界的に知られるパリの観光名所およそ２０か所を映像でめぐります。<br /><br />ドローンを使って撮影した上空からの風景を上下左右、利用客の動きに合わせて自由に楽しめるのが特徴で、まるでパリ市内を空中散歩しているように感じることができるということです。<br /><br />「ＶＲ観光」を体験した男性は、「冒険のようでとても楽しめました。これまで見たことがないパリを知ることができます」と話していました。<br /><br />施設は今月３１日にオープンする予定で、これまでとは少し違った視点からパリの観光を楽しめると話題を集めそうです。",
      "textPos": "bottom"
    }
  ],
  "relationNews": [
    {
      "link": "html/20180324/k10011377281000.html",
      "title": "フェイスブックのザッカーバーグ氏に証言要請 米議会",
      "date": "3月24日  10時04分",
      "datetime": "2018-03-24T10:04",
      "imgPath": "html/20180324/K10011377281_1803241009_1803241012_01_02.jpg",
      "iconPath": "html/20180324/K10011377281_1803241009_1803241012_02_01.jpg",
      "video": "",
      "duration": 0
    },
    {
      "link": "html/20180324/k10011377261000.html",
      "title": "ＡＩやロボットは脅威？安全保障への影響など考える会合",
      "date": "3月24日  8時41分",
      "datetime": "2018-03-24T08:41",
      "imgPath": "html/20180324/K10011377261_1803241029_1803241034_01_02.jpg",
      "iconPath": "html/20180324/K10011377261_1803241029_1803241034_02_01.jpg",
      "video": "",
      "duration": 0
    }
  ],
  "relationLink": [
    {
      "link": "https://www3.nhk.or.jp/news/easy/k10011383361000/k10011383361000.html",
      "title": "バーチャルリアリティーの技術を使ってパリの空を散歩",
      "time": "NEWSWEB EASY 3月30日",
      "datetime": "2018-03-30"
    },
    {
      "link": "//www3.nhk.or.jp/news/business_tokushu/2017_0502.html",
      "title": "今 注目されるＭＲ＝複合現実って何？",
      "time": "ビジネス特集 5月2日",
      "datetime": "2017-05-02"
    }
  ],
  "word": [
    {
      "link": "word/0000009.html",
      "title": "IT・ネット"
    }
  ],
  "news_id": "k10011383361000",
  "yyyy": "2018",
  "mm": "03",
  "dd": "29",
  "url": "https://www3.nhk.or.jp/news/html/20180329/k10011383361000.html"
}