{
  "news_id": "k10011364661000",
  "news_prearranged_time": "2018-03-15 16:50:00",
  "title": "宇宙の研究で有名なホーキング博士が亡くなる",
  "title_with_ruby": "<ruby>宇宙<rt>うちゅう</rt></ruby>の<ruby>研究<rt>けんきゅう</rt></ruby>で<ruby>有名<rt>ゆうめい</rt></ruby>なホーキング<ruby>博士<rt>はかせ</rt></ruby>が<ruby>亡<rt>な</rt></ruby>くなる",
  "outline_with_ruby": "<p><a href='javascript:void(0)' class='dicWin' id='id-0000'><ruby>宇宙<rt>うちゅう</rt></ruby></a>がどうやってできたかや<a href='javascript:void(0)' class='dicWin' id='id-0002'>ブラックホール</a>などについて<ruby>研究<rt>けんきゅう</rt></ruby>したスティーブン・ホーキング<a href='javascript:void(0)' class='dicWin' id='id-0001'><ruby>博士<rt>はかせ</rt></ruby></a>が<ruby>１４日<rt>じゅうよっか</rt></ruby>、７６<ruby>歳<rt>さい</rt></ruby>で<ruby>亡<rt>な</rt></ruby>くなりました。",
  "has_news_web_image": true,
  "has_news_web_movie": true,
  "has_news_easy_image": false,
  "has_news_easy_movie": false,
  "has_news_easy_voice": true,
  "news_web_image_uri": "https://www3.nhk.or.jp/news/html/20180314/../20180314/K10011364661_1803141308_1803141313_01_03.jpg",
  "news_web_movie_uri": "k10011364661_201803141308_201803141313.mp4",
  "news_easy_image_uri": "''",
  "news_easy_movie_uri": "''",
  "news_easy_voice_uri": "k10011364661000.mp3",
  "url": "http://www3.nhk.or.jp/news/easy/k10011364661000/k10011364661000.html"
}