{
  "cate": "8",
  "date": "3æ8æ¥ 12æ05å",
  "datetime": "2018-03-08T12:05",
  "video": "/news/html/20180308/movie/k10011355291_201803081217_201803081218.html",
  "duration": 65,
  "img": "html/20180308/K10011355291_1803080614_1803080619_01_02.jpg",
  "title": "新燃岳 噴火活動が活発化 大きな噴石や火砕流に警戒を",
  "summary": "鹿児島と宮崎の県境にある霧島連山の新燃岳では、６日から大きな噴石を火口の外まで飛ばす爆発的な噴火が相次いでいます。７日には放出される火山ガスが急増するなど噴火活動が活発化していて、気象庁は、噴火警戒レベル３を継続し、大きな噴石や火砕流に警戒するよう呼びかけています。",
  "more": "気象庁によりますと、霧島連山の新燃岳では今月１日から噴火が続いていて、空振と呼ばれる空気の振動を伴う爆発的な噴火が、６日は１８回、７日は１６回観測され、一連の噴火では大きな噴石が火口から最大７００メートルまで飛び、噴煙が最大で３０００メートルに達したことが確認されています。<br /><br />８日は午前中、雲がかかっていて噴煙や火口付近の状況はわかりませんが、８日も火山性地震も多い状態が続き、空振を伴う振幅の大きな地震も起きているほか、火山性微動の振幅が大きい状態が続くなど、噴火は継続していると見られるということです。<br /><br />新燃岳では、７日までの調査や観測で火口内にたまった溶岩が急速に大きくなっていることや、火山ガスの二酸化硫黄の放出量が７日には３万４０００トンと、今月２日の１５倍に急増するなど噴火活動が活発化しています。<br /><br />気象庁は、今後さらに火山活動が高まる可能性があるとして、「入山規制」を示す噴火警戒レベル「３」を継続し、火口からおおむね３キロの範囲では噴火に伴う大きな噴石に、おおむね２キロの範囲では火砕流にそれぞれ警戒するよう呼びかけています。<br /><br />また火山灰や小さな噴石、火山ガス、それに爆発的な噴火に伴う空振に注意するとともに、火山灰が降り積もった地域では大雨の際の土石流にも注意するよう呼びかけています。",
  "body": [
    {
      "title": "",
      "img": "",
      "align": "",
      "text": "",
      "textPos": ""
    }
  ],
  "relationNews": [
    {
      "link": "html/20180307/k10011354781000.html",
      "title": "新燃岳で爆発的噴火相次ぐ 大きな噴石や火砕流に警戒を",
      "date": "3月7日  19時49分",
      "datetime": "2018-03-07T19:49",
      "imgPath": "html/20180307/K10011354781_1803071802_1803071834_01_02.jpg",
      "iconPath": "html/20180307/K10011354781_1803071802_1803071834_02_01.jpg",
      "video": "https://www3.nhk.or.jp/news/html/20180307/movie/k10011354781_201803072004_201803072011.html",
      "duration": 167
    },
    {
      "link": "html/20180306/k10011353261000.html",
      "title": "陸自演習場で作業員２人死亡 土石流に流されたか 静岡",
      "date": "3月6日  13時04分",
      "datetime": "2018-03-06T13:04",
      "imgPath": "html/20180306/K10011353261_1803061514_1803061514_01_03.jpg",
      "iconPath": "html/20180306/K10011353261_1803061514_1803061514_02_01.jpg",
      "video": "https://www3.nhk.or.jp/news/html/20180306/movie/k10011353261_201803061514_201803061514.html",
      "duration": 63
    }
  ],
  "relationLink": [
    {
      "link": "http://www3.nhk.or.jp/lnews/miyazaki/",
      "title": "NHK宮崎放送局",
      "time": "各地のニュース",
      "datetime": ""
    },
    {
      "link": "http://www3.nhk.or.jp/lnews/kagoshima/",
      "title": "NHK鹿児島放送局",
      "time": "各地のニュース",
      "datetime": ""
    }
  ],
  "word": [
    {
      "link": "word/0000430.html",
      "title": "新燃岳"
    }
  ],
  "news_id": "k10011355291000",
  "yyyy": "2018",
  "mm": "03",
  "dd": "08",
  "url": "https://www3.nhk.or.jp/news/html/20180308/k10011355291000.html"
}